serialmecab/__init__.py
serialmecab/tokenizer.py
serialmecab/types.py
tests/__init__.py
tests/test_tokenizer.py
serial_mecab-1.1.0.dist-info/METADATA
serial_mecab-1.1.0.dist-info/WHEEL
serial_mecab-1.1.0.dist-info/top_level.txt
serial_mecab-1.1.0.dist-info/RECORD
