Metadata-Version: 2.1
Name: serial-mecab
Version: 1.1.0
Summary: mecab-python3 wrapper for serialization
Home-page: UNKNOWN
License: UNKNOWN
Platform: UNKNOWN
Requires-Dist: mecab-python3
Requires-Dist: joblib
Provides-Extra: dev
Requires-Dist: ipython ; extra == 'dev'
Requires-Dist: python-language-server[all] ; extra == 'dev'
Provides-Extra: doc
Requires-Dist: sphinx ; extra == 'doc'
Requires-Dist: sphinx-rtd-theme ; extra == 'doc'
Provides-Extra: test
Requires-Dist: pytest ; extra == 'test'
